README.txt
setup.py
prod_cal.egg-info/PKG-INFO
prod_cal.egg-info/SOURCES.txt
prod_cal.egg-info/dependency_links.txt
prod_cal.egg-info/top_level.txt
prodcal/__init__.py
prodcal/config.py
prodcal/holidays.py
prodcal/service.py
prodcal/prodcals/__init__.py
prodcal/prodcals/by.py
prodcal/prodcals/ge.py
prodcal/prodcals/kz.py
prodcal/prodcals/prod_dict.py
prodcal/prodcals/ru.py
prodcal/prodcals/ua.py