Metadata-Version: 1.1
Name: prod-cal
Version: 0.1b6
Summary: Given module allows to use production calendars of different countries
Home-page: https://github.com/balamut108/prod-cal
Author: Vladimir Sidorov
Author-email: vladimir.sidorov@raziogroup.com
License: Apache 2.0
Platform: UNKNOWN
Classifier: Development Status :: 4 - Beta
Classifier: Environment :: Console
Classifier: License :: Freeware
Classifier: License :: OSI Approved :: Apache Software License
Classifier: Natural Language :: English
Classifier: Programming Language :: Python :: 2.7
Classifier: Topic :: Office/Business
Classifier: Topic :: Office/Business :: Scheduling
Classifier: Topic :: Utilities
